factornado/__init__.py
factornado/application.py
factornado/authentication.py
factornado/handlers.py
factornado/logger.py
factornado/tasks.py
factornado/utils.py
factornado-0.11.0.dist-info/DESCRIPTION.rst
factornado-0.11.0.dist-info/METADATA
factornado-0.11.0.dist-info/RECORD
factornado-0.11.0.dist-info/WHEEL
factornado-0.11.0.dist-info/metadata.json
factornado-0.11.0.dist-info/top_level.txt
