Metadata-Version: 2.0
Name: factornado
Version: 0.11.0
Summary: Factory for creating microservices with tornado
Home-page: https://github.com/factornado/factornado
Author: Martin Journois
Author-email: martin@journois.fr
License: Copyright (C) 2016, Martin Journois
Requires-Dist: pandas
Requires-Dist: pyjwt
Requires-Dist: pymongo
Requires-Dist: pyyaml
Requires-Dist: requests
Requires-Dist: tornado
